setup.py
yunpian/Config.py
yunpian/DES.py
yunpian/FlowOperator.py
yunpian/HttpUtil.py
yunpian/Sign.py
yunpian/SmsOperator.py
yunpian/Tea.py
yunpian/TplOperator.py
yunpian/UserOperator.py
yunpian/VoiceOperator.py
yunpian/__init__.py
yunpian/model/Result.py
yunpian/model/__init__.py
yunpian/test/YunpianRestTest.py
yunpian/test/__init__.py
yunpian_sdk_python.egg-info/PKG-INFO
yunpian_sdk_python.egg-info/SOURCES.txt
yunpian_sdk_python.egg-info/dependency_links.txt
yunpian_sdk_python.egg-info/requires.txt
yunpian_sdk_python.egg-info/top_level.txt