Metadata-Version: 1.0
Name: yunpian-sdk-python
Version: 0.0.5
Summary: yunpian-sdk-python
Home-page: UNKNOWN
Author: bingone
Author-email: shaoyan@yunpian.com
License: MIT License
Keywords: yunpian,sdk,python
Platform: any
